Metadata-Version: 1.1
Name: gitlabbuildvariables
Version: 1.1.0
Summary: Tools for dealing with GitLab CI build variables
Home-page: https://github.com/wtsi-hgi/gitlab-build-variables
Author: Colin Nolan
Author-email: colin.nolan@sanger.ac.uk
License: GPL3
Platform: UNKNOWN
Classifier: Development Status :: 5 - Production/Stable
Classifier: Operating System :: OS Independent
Classifier: Programming Language :: Python :: 3.6
Classifier: License :: OSI Approved :: GNU General Public License v3 (GPLv3)
